aioinflux/__init__.py
aioinflux/client.py
aioinflux/compat.py
aioinflux/iterutils.py
aioinflux/serialization/__init__.py
aioinflux/serialization/common.py
aioinflux/serialization/dataframe.py
aioinflux/serialization/mapping.py
aioinflux/serialization/usertype.py
aioinflux-0.9.0.dist-info/LICENSE
aioinflux-0.9.0.dist-info/METADATA
aioinflux-0.9.0.dist-info/WHEEL
aioinflux-0.9.0.dist-info/top_level.txt
aioinflux-0.9.0.dist-info/RECORD
