Metadata-Version: 2.1
Name: aioinflux
Version: 0.9.0
Summary: Asynchronous Python client for InfluxDB
Home-page: https://github.com/gusutabopb/aioinflux
Author: Gustavo Bezerra
Author-email: gusutabopb@gmail.com
License: UNKNOWN
Platform: UNKNOWN
Classifier: Development Status :: 4 - Beta
Classifier: Intended Audience :: Developers
Classifier: License :: OSI Approved :: MIT License
Classifier: Programming Language :: Python :: 3.6
Classifier: Programming Language :: Python :: 3.7
Classifier: Topic :: Database
Requires-Python: >=3.6
Requires-Dist: aiohttp (>=3.0)
Requires-Dist: ciso8601
Provides-Extra: cache
Requires-Dist: aioredis (>=1.2.0) ; extra == 'cache'
Requires-Dist: lz4 (>=2.1.0) ; extra == 'cache'
Provides-Extra: docs
Requires-Dist: docutils ; extra == 'docs'
Requires-Dist: sphinx ; extra == 'docs'
Requires-Dist: sphinx-rtd-theme ; extra == 'docs'
Requires-Dist: sphinx-autodoc-typehints ; extra == 'docs'
Provides-Extra: pandas
Requires-Dist: pandas (>=0.21) ; extra == 'pandas'
Requires-Dist: numpy ; extra == 'pandas'
Provides-Extra: test
Requires-Dist: pytest ; extra == 'test'
Requires-Dist: pytest-asyncio ; extra == 'test'
Requires-Dist: pytest-cov ; extra == 'test'
Requires-Dist: pyyaml ; extra == 'test'
Requires-Dist: pytz ; extra == 'test'
Requires-Dist: flake8 ; extra == 'test'
Requires-Dist: pep8-naming ; extra == 'test'
Requires-Dist: flake8-rst-docstrings ; extra == 'test'
Requires-Dist: pygments ; extra == 'test'
Requires-Dist: dataclasses ; extra == 'test'
